fsspeckit/__init__.py
fsspeckit/py.typed
fsspeckit/common/__init__.py
fsspeckit/common/datetime.py
fsspeckit/common/logging_config.py
fsspeckit/common/misc.py
fsspeckit/common/optional.py
fsspeckit/common/partitions.py
fsspeckit/common/polars.py
fsspeckit/common/schema.py
fsspeckit/common/security.py
fsspeckit/common/types.py
fsspeckit/common/logging/__init__.py
fsspeckit/common/logging/config.py
fsspeckit/core/__init__.py
fsspeckit/core/base.py
fsspeckit/core/filesystem.py
fsspeckit/core/filesystem_cache.py
fsspeckit/core/filesystem_paths.py
fsspeckit/core/incremental.py
fsspeckit/core/maintenance.py
fsspeckit/core/merge.py
fsspeckit/core/ext/__init__.py
fsspeckit/core/ext/csv.py
fsspeckit/core/ext/dataset.py
fsspeckit/core/ext/io.py
fsspeckit/core/ext/json.py
fsspeckit/core/ext/parquet.py
fsspeckit/core/ext/register.py
fsspeckit/core/filesystem/__init__.py
fsspeckit/core/filesystem/cache.py
fsspeckit/core/filesystem/gitlab.py
fsspeckit/core/filesystem/paths.py
fsspeckit/datasets/__init__.py
fsspeckit/datasets/base.py
fsspeckit/datasets/duckdb_cleanup_helpers.py
fsspeckit/datasets/exceptions.py
fsspeckit/datasets/interfaces.py
fsspeckit/datasets/path_utils.py
fsspeckit/datasets/write_result.py
fsspeckit/datasets/duckdb/__init__.py
fsspeckit/datasets/duckdb/connection.py
fsspeckit/datasets/duckdb/dataset.py
fsspeckit/datasets/duckdb/exceptions.py
fsspeckit/datasets/duckdb/helpers.py
fsspeckit/datasets/pyarrow/__init__.py
fsspeckit/datasets/pyarrow/adaptive_tracker.py
fsspeckit/datasets/pyarrow/dataset.py
fsspeckit/datasets/pyarrow/io.py
fsspeckit/datasets/pyarrow/memory.py
fsspeckit/datasets/pyarrow/schema.py
fsspeckit/sql/__init__.py
fsspeckit/sql/filters/__init__.py
fsspeckit/storage_options/__init__.py
fsspeckit/storage_options/base.py
fsspeckit/storage_options/cloud.py
fsspeckit/storage_options/core.py
fsspeckit/storage_options/git.py
fsspeckit/utils/__init__.py
fsspeckit/utils/misc.py
fsspeckit/utils/polars.py
fsspeckit/utils/pyarrow.py
fsspeckit/utils/sql.py
fsspeckit-0.10.0.dist-info/METADATA
fsspeckit-0.10.0.dist-info/WHEEL
fsspeckit-0.10.0.dist-info/licenses/LICENSE
fsspeckit-0.10.0.dist-info/RECORD
