Metadata-Version: 2.4
Name: fsspeckit
Version: 0.10.0
Summary: Enhanced utilities and extensions for fsspec, storage_options and obstore with multi-format I/O support.
Project-URL: Homepage, https://github.com/legout/fsspeckit
Project-URL: Documentation, https://legout.github.io/fsspeckit
Project-URL: Repository, https://github.com/legout/fsspeckit.git
Project-URL: Issues, https://github.com/legout/fsspeckit/issues
Author-email: legout <ligno.blades@gmail.com>
License-Expression: MIT
License-File: LICENSE
Keywords: azure,cloud-storage,csv,data-io,filesystem,fsspec,gcs,json,object-storage,obstore,parquet,s3
Classifier: Development Status :: 4 - Beta
Classifier: Intended Audience :: Developers
Classifier: License :: OSI Approved :: MIT License
Classifier: Operating System :: OS Independent
Classifier: Programming Language :: Python :: 3
Classifier: Programming Language :: Python :: 3.11
Classifier: Programming Language :: Python :: 3.12
Classifier: Topic :: Scientific/Engineering :: Information Analysis
Classifier: Topic :: Software Development :: Libraries :: Python Modules
Classifier: Topic :: System :: Filesystems
Requires-Python: >=3.11
Requires-Dist: fsspec>=2025.1.0
Requires-Dist: joblib>=1.5.0
Requires-Dist: loguru>=0.7.0
Requires-Dist: mcp>=1.23.1
Requires-Dist: msgspec>=0.18.0
Requires-Dist: numpy>=2.3.5
Requires-Dist: obstore>=0.8.2
Requires-Dist: openai>=2.12.0
Requires-Dist: orjson>=3.11.4
Requires-Dist: pandas>=2.3.3
Requires-Dist: polars>=1.35.2
Requires-Dist: pyarrow>=22.0.0
Requires-Dist: pyyaml>=6.0
Requires-Dist: requests>=2.25.0
Requires-Dist: rich>=14.0.0
Provides-Extra: aws
Requires-Dist: boto3>=1.26.0; extra == 'aws'
Requires-Dist: s3fs>=2025.1.0; extra == 'aws'
Provides-Extra: azure
Requires-Dist: adlfs>=2024.12.0; extra == 'azure'
Provides-Extra: datasets
Requires-Dist: duckdb>=1.4.0; extra == 'datasets'
Requires-Dist: orjson>=3.11.0; extra == 'datasets'
Requires-Dist: pandas>=2.2.0; extra == 'datasets'
Requires-Dist: polars>=1.30.0; extra == 'datasets'
Requires-Dist: psutil>=5.9.0; extra == 'datasets'
Requires-Dist: pyarrow>=20.0.0; extra == 'datasets'
Requires-Dist: sqlglot>=27.16.3; extra == 'datasets'
Provides-Extra: gcp
Requires-Dist: gcsfs>=2025.1.0; extra == 'gcp'
Provides-Extra: monitoring
Requires-Dist: psutil>=5.9.0; extra == 'monitoring'
Provides-Extra: polars
Requires-Dist: polars>=1.30.0; extra == 'polars'
Provides-Extra: sql
Requires-Dist: duckdb>=1.4.0; extra == 'sql'
Requires-Dist: orjson>=3.11.0; extra == 'sql'
Requires-Dist: sqlglot>=27.16.3; extra == 'sql'
